Assignment2/convolution.v
module convolvolution (
  input  [3:0] x [7:0],   
  input  [3:0] h [7:0],   
  output reg [3:0] y [14:0]   
);

integer n, k, j;
always @(*) begin
  for (n = 0; n < 15; n = n + 1) begin 
    y[n] = 4'd0;
  end
  for (j=0; j < 8; j = j + 1) begin
    for (k = 0; k < 8; k = k + 1) begin
      y[j+k] += x[j]*h[k];
      /*if ((n - k) >= 0 && (n - k) < 8) begin
        y[n] += (x[k] * h[n - k]);
      end*/
    end
  end
end
endmodule

`timescale 1ns / 1ns

module tb_conv;
    reg [3:0] x[7:0];
    reg [3:0] h[7:0];
    wire [3:0] y[14:0];

    convolvolution dut(.x(x), .h(h), .y(y));

    initial begin
        $dumpfile("conv.vcd");
        $dumpvars(0, tb_conv);

        for (integer i = 0; i < 8; i++) begin
            $dumpvars(0, tb_conv.x[i]);
            $dumpvars(0, tb_conv.h[i]);
        end

        for (integer i = 0; i < 15; i++) begin
            $dumpvars(0, tb_conv.y[i]);
        end

        $monitor("x = [%d, %d, %d, %d, %d, %d, %d, %d]\nh = [%d, %d, %d, %d, %d, %d, %d, %d]\nx*h = [%d, %d, %d, %d, %d, %d, %d, %d, %d, %d, %d, %d, %d, %d, %d]\n", x[0], x[1], x[2], x[3], x[4], x[5], x[6], x[7], h[0], h[1], h[2], h[3], h[4], h[5], h[6], h[7], y[0], y[1], y[2], y[3], y[4], y[5], y[6], y[7], y[8], y[9], y[10], y[11], y[12], y[13], y[14]);

        x[0] = 4'd1; x[1] = 4'd2; x[2] = 4'd3; x[3] = 4'd4;
        x[4] = 4'd0; x[5] = 4'd1; x[6] = 4'd0; x[7] = 4'd1;
        h[0] = 4'd1; h[1] = 4'd0; h[2] = 4'd1; h[3] = 4'd0;
        h[4] = 4'd1; h[5] = 4'd0; h[6] = 4'd1; h[7] = 4'd0;
        #10;

        x[0] = 4'd1; x[1] = 4'd1; x[2] = 4'd1; x[3] = 4'd1;
        x[4] = 4'd1; x[5] = 4'd1; x[6] = 4'd1; x[7] = 4'd1;
        h[0] = 4'd1; h[1] = 4'd1; h[2] = 4'd1; h[3] = 4'd1;
        h[4] = 4'd1; h[5] = 4'd1; h[6] = 4'd1; h[7] = 4'd1;
        #10;

        x[0] = 4'd1; x[1] = 4'd0; x[2] = 4'd1; x[3] = 4'd0;
        x[4] = 4'd1; x[5] = 4'd0; x[6] = 4'd1; x[7] = 4'd0;
        h[0] = 4'd1; h[1] = 4'd0; h[2] = 4'd1; h[3] = 4'd0;
        h[4] = 4'd1; h[5] = 4'd0; h[6] = 4'd1; h[7] = 4'd0;
        #10;

        x[0] = 4'd1; x[1] = 4'd2; x[2] = 4'd3; x[3] = 4'd4;
        x[4] = 4'd5; x[5] = 4'd6; x[6] = 4'd7; x[7] = 4'd8;
        h[0] = 4'd1; h[1] = 4'd1; h[2] = 4'd1; h[3] = 4'd1;
        h[4] = 4'd1; h[5] = 4'd1; h[6] = 4'd1; h[7] = 4'd1;
        #10;

        x[0] = 4'd5; x[1] = 4'd5; x[2] = 4'd5; x[3] = 4'd5;
        x[4] = 4'd5; x[5] = 4'd5; x[6] = 4'd5; x[7] = 4'd5;
        h[0] = 4'd1; h[1] = 4'd2; h[2] = 4'd3; h[3] = 4'd4;
        h[4] = 4'd5; h[5] = 4'd6; h[6] = 4'd7; h[7] = 4'd8;
        #10;

        x[0] = 4'd15; x[1] = 4'd15; x[2] = 4'd15; x[3] = 4'd15;
        x[4] = 4'd15; x[5] = 4'd15; x[6] = 4'd15; x[7] = 4'd15;
        h[0] = 4'd15; h[1] = 4'd15; h[2] = 4'd15; h[3] = 4'd15;
        h[4] = 4'd15; h[5] = 4'd15; h[6] = 4'd15; h[7] = 4'd15;
        #10;

        x[0] = 4'd1; x[1] = 4'd0; x[2] = 4'd0; x[3] = 4'd0;
        x[4] = 4'd0; x[5] = 4'd0; x[6] = 4'd0; x[7] = 4'd0;
        h[0] = 4'd2; h[1] = 4'd3; h[2] = 4'd4; h[3] = 4'd5;
        h[4] = 4'd6; h[5] = 4'd7; h[6] = 4'd8; h[7] = 4'd9;
        #10;

        x[0] = 4'd7; x[1] = 4'd3; x[2] = 4'd9; x[3] = 4'd2;
        x[4] = 4'd5; x[5] = 4'd1; x[6] = 4'd8; x[7] = 4'd4;
        h[0] = 4'd6; h[1] = 4'd2; h[2] = 4'd7; h[3] = 4'd1;
        h[4] = 4'd9; h[5] = 4'd3; h[6] = 4'd5; h[7] = 4'd8;
        #10;

        $finish;
    end

endmodule

Assignment2/conv.vcd
$date
	Mon Apr 21 12:40:35 2025
$end
$version
	Icarus Verilog
$end
$timescale
	1ns
$end
$scope module tb_conv $end
$scope module dut $end
$var integer 32 ! j [31:0] $end
$var integer 32 " k [31:0] $end
$var integer 32 # n [31:0] $end
$upscope $end
$scope begin $ivl_for_loop0 $end
$var integer 32 $ i [31:0] $end
$upscope $end
$scope begin $ivl_for_loop1 $end
$var integer 32 % i [31:0] $end
$upscope $end
$upscope $end
$scope module tb_conv $end
$var reg 4 & \x[0] [3:0] $end
$upscope $end
$scope module tb_conv $end
$var reg 4 ' \h[0] [3:0] $end
$upscope $end
$scope module tb_conv $end
$var reg 4 ( \x[1] [3:0] $end
$upscope $end
$scope module tb_conv $end
$var reg 4 ) \h[1] [3:0] $end
$upscope $end
$scope module tb_conv $end
$var reg 4 * \x[2] [3:0] $end
$upscope $end
$scope module tb_conv $end
$var reg 4 + \h[2] [3:0] $end
$upscope $end
$scope module tb_conv $end
$var reg 4 , \x[3] [3:0] $end
$upscope $end
$scope module tb_conv $end
$var reg 4 - \h[3] [3:0] $end
$upscope $end
$scope module tb_conv $end
$var reg 4 . \x[4] [3:0] $end
$upscope $end
$scope module tb_conv $end
$var reg 4 / \h[4] [3:0] $end
$upscope $end
$scope module tb_conv $end
$var reg 4 0 \x[5] [3:0] $end
$upscope $end
$scope module tb_conv $end
$var reg 4 1 \h[5] [3:0] $end
$upscope $end
$scope module tb_conv $end
$var reg 4 2 \x[6] [3:0] $end
$upscope $end
$scope module tb_conv $end
$var reg 4 3 \h[6] [3:0] $end
$upscope $end
$scope module tb_conv $end
$var reg 4 4 \x[7] [3:0] $end
$upscope $end
$scope module tb_conv $end
$var reg 4 5 \h[7] [3:0] $end
$upscope $end
$scope module tb_conv $end
$var reg 4 6 \y[0] [3:0] $end
$upscope $end
$scope module tb_conv $end
$var reg 4 7 \y[1] [3:0] $end
$upscope $end
$scope module tb_conv $end
$var reg 4 8 \y[2] [3:0] $end
$upscope $end
$scope module tb_conv $end
$var reg 4 9 \y[3] [3:0] $end
$upscope $end
$scope module tb_conv $end
$var reg 4 : \y[4] [3:0] $end
$upscope $end
$scope module tb_conv $end
$var reg 4 ; \y[5] [3:0] $end
$upscope $end
$scope module tb_conv $end
$var reg 4 < \y[6] [3:0] $end
$upscope $end
$scope module tb_conv $end
$var reg 4 = \y[7] [3:0] $end
$upscope $end
$scope module tb_conv $end
$var reg 4 > \y[8] [3:0] $end
$upscope $end
$scope module tb_conv $end
$var reg 4 ? \y[9] [3:0] $end
$upscope $end
$scope module tb_conv $end
$var reg 4 @ \y[10] [3:0] $end
$upscope $end
$scope module tb_conv $end
$var reg 4 A \y[11] [3:0] $end
$upscope $end
$scope module tb_conv $end
$var reg 4 B \y[12] [3:0] $end
$upscope $end
$scope module tb_conv $end
$var reg 4 C \y[13] [3:0] $end
$upscope $end
$scope module tb_conv $end
$var reg 4 D \y[14] [3:0] $end
$upscope $end
$enddefinitions $end
$comment Show the parameter values. $end
$dumpall
$end
#0
$dumpvars
b0 D
b1 C
b0 B
b10 A
b0 @
b110 ?
b11 >
b1000 =
b100 <
b111 ;
b100 :
b110 9
b100 8
b10 7
b1 6
b0 5
b1 4
b1 3
b0 2
b0 1
b1 0
b1 /
b0 .
b0 -
b100 ,
b1 +
b11 *
b0 )
b10 (
b1 '
b1 &
b1111 %
b1000 $
b1111 #
b1000 "
b1000 !
$end
#10
b1 D
b11 B
b101 @
b1000 "
b1000 !
b10 C
b100 A
b110 ?
b111 >
b1000 =
b111 <
b110 ;
b101 :
b100 9
b11 8
b10 7
b1 6
b1111 #
b1 5
b1 3
b1 1
b1 /
b1 -
b1 +
b1 )
b1 '
b1 4
b1 2
b1 0
b1 .
b1 ,
b1 *
b1 (
b1 &
#20
b1000 "
b1000 !
b0 D
b0 C
b1 B
b0 A
b10 @
b0 ?
b11 >
b0 =
b100 <
b0 ;
b11 :
b0 9
b10 8
b0 7
b1 6
b1111 #
b0 5
b1 3
b0 1
b1 /
b0 -
b1 +
b0 )
b1 '
b0 4
b1 2
b0 0
b1 .
b0 ,
b1 *
b0 (
b1 &
#30
b1000 D
b1111 C
b1010 A
b1 ?
b100 =
b101 ;
b1010 9
b11 7
b1000 "
b1000 !
b101 B
b1110 @
b11 >
b1100 <
b1111 :
b110 8
b1 6
b1111 #
b1 5
b1 3
b1 1
b1 /
b1 -
b1 +
b1 )
b1 '
b1000 4
b111 2
b110 0
b101 .
b100 ,
b11 *
b10 (
b1 &
#40
b1000 "
b1000 !
b1000 D
b1011 C
b1001 B
b10 A
b110 @
b101 ?
b1111 >
b100 =
b1100 <
b1001 ;
b1011 :
b10 9
b1110 8
b1111 7
b101 6
b1111 #
b1000 5
b111 3
b110 1
b101 /
b100 -
b11 +
b10 )
b1 '
b101 4
b101 2
b101 0
b101 .
b101 ,
b101 *
b101 (
b101 &
#50
b1000 "
b1000 !
b1 D
b10 C
b11 B
b100 A
b101 @
b110 ?
b111 >
b1000 =
b111 <
b110 ;
b101 :
b100 9
b11 8
b10 7
b1 6
b1111 #
b1111 5
b1111 3
b1111 1
b1111 /
b1111 -
b1111 +
b1111 )
b1111 '
b1111 4
b1111 2
b1111 0
b1111 .
b1111 ,
b1111 *
b1111 (
b1111 &
#60
b1000 "
b1000 !
b0 D
b0 C
b0 B
b0 A
b0 @
b0 ?
b0 >
b1001 =
b1000 <
b111 ;
b110 :
b101 9
b100 8
b11 7
b10 6
b1111 #
b1001 5
b1000 3
b111 1
b110 /
b101 -
b100 +
b11 )
b10 '
b0 4
b0 2
b0 0
b0 .
b0 ,
b0 *
b0 (
b1 &
#70
b100 C
b1100 B
b1001 A
b1000 @
b1110 ?
b1001 >
b1000 "
b1000 !
b1000 =
b100 <
b111 ;
b11 :
b1010 9
b1101 8
b0 7
b1010 6
b1111 #
b1000 5
b101 3
b11 1
b1001 /
b1 -
b111 +
b10 )
b110 '
b100 4
b1000 2
b1 0
b101 .
b10 ,
b1001 *
b11 (
b111 &
