FinalProject/digital_clock.v
/*
*
  * Mode 1: See time (12 Hr) and Date
  * Mode 2: See time (24hr) and Date
  * Mode 3: Set Time, Date Manually
  * Mode 4: Set Alarm
  * Mode 5: Set Timer 
  * Mode 6: Resetting Date and Time to 1 Jan 2024 12 AM
  * Input Formats:
    * Mode 3: 3 <HH> <MM> <SS> <DD>  <MM> <YY>
    * Mode 1: 1 
    * Mode 2: 2 
    * Mode 4: 4 <HH> <MM> <SS> (in 24 hr format)
    * Mode 5: 5 <MM> <SS> 
    * Mode 6: 6
      */

     `timescale 1s/1ms

     module digital_clock(
       input clk,
       // For Mode 3 (Setting Time, Date manually)
       input reset,
       input [4:0] set_hour,
       input [5:0] set_min,
       input [5:0] set_sec,
       input [4:0] set_day,
       input [3:0] set_month,
       input [11:0] set_year,

       // For Mode 4 (Alarm)
       input [4:0] alarm_hour,
       input [5:0] alarm_min,
       input [5:0] alarm_sec,
       input alarm_enable,

       // For Mode 5 (Timer)
       input [5:0] timer_min,
       input [5:0] timer_sec,
       input timer_enable,

       // Time Related
       output reg [4:0] hour,
       output reg AM_enabled,
       output reg [5:0] min,
       output reg [5:0] sec,
       output reg [4:0] day,
       output reg [3:0] month,
       output reg [11:0] year,
       output reg [2:0] day_of_week,

       output reg [5:0] timer_count_min,
       output reg [5:0] timer_count_sec,
       output reg alarm_buzzer,
       output reg timer_buzzer
       );

       //reg timer_running = 0;
       //reg alarm_triggered = 0;

       // Setting inital values for some parameters
       initial begin
         hour = 0; min = 0; sec = 0;
         day = 1; month = 1; year = 2020;
         alarm_buzzer = 0;
         AM_enabled = 0;
         timer_buzzer = 0;
         timer_count_sec = 0;
         timer_count_min = 0;
       end

       // To calculate day (given date, month, year)
       function [2:0] calc_day_of_week;
         input [4:0] d;
         input [3:0] m;
         input [11:0] y;
         reg [11:0] yy;
         reg [3:0] mm;
         begin
           yy = y;
           mm = m;
           if (mm < 3) begin 
             mm = mm + 12;
             yy = yy - 1;
           end // Calculating using Zeller's Congruence  
           calc_day_of_week = ((d + (13*(mm+1))/5 + yy + (yy/4) - (yy/100) + (yy/400))-1) % 7;
         end
       endfunction

       // Calculating number of days in a month
       function [5:0] days_in_month;
         input [3:0] m;
         input [11:0] y;
         begin
           case (m) // case statement for number of days in each month
             1,3,5,7,8,10,12: days_in_month = 31; 
             4,6,9,11: days_in_month = 30;
             2: days_in_month = ((y % 4 == 0 && y % 100 != 0) || (y % 400 == 0)) ? 29 : 28; // Leap Years
             default: days_in_month = 30;
           endcase
         end
       endfunction

       always @(posedge clk or posedge reset) begin 
         
         if (reset) begin // Manual Reset (Mode 3)
           hour <= set_hour;
           min <= set_min;
           sec <= set_sec;
           day <= set_day;
           month <= set_month;
           year <= set_year;
         end else begin
           // Updating clock
           // We change the value one cycle before it actually has to reflect
           // due to non blocking statements used which are read at the next
           // positive edge of the clock
           sec <= sec + 1;
           // AM_enabled <= (hour < 12); 
           // Setting signal which indicates 'AM' or 'PM'
           if(hour == 23 && min == 59 && sec == 59) AM_enabled = 1; 
           else AM_enabled = (hour < 12);

           // Manual reset after april 2025 to january 2020
           if (day == 30 && month == 4 && year == 2025 && hour == 23 && min == 59 && sec == 59) begin 
             day <= 1;
             month <= 1; 
             year <= 2020;
             hour <= 0; 
             min <= 0;
             sec <= 0;
           end else if (sec == 59) begin // Normal incrementing Date and Time otherwise
             sec <= 0;
             min <= min + 1;
             if (min == 59) begin
               min <= 0;
               hour <= hour + 1;
               if (hour == 23) begin
                 hour <= 0;
                 day <= day + 1;
                 if (day > days_in_month(month, year)-1) begin
                   day <= 1;
                   month <= month + 1;
                   if (month > 11) begin
                     month <= 1;
                     year <= year + 1;
                     if (year > 2025) year <= 2020;
                   end
               end
             end
           end
         end
         // Updating Day 
         // Setting day seperately for last second of day (non blocking
         // assignment)
         if (hour == 23 && min == 59 && sec == 59 && day != 30 && month != 4 && year != 2025) begin 
           day_of_week <= calc_day_of_week(day+1, month, year);
         end 
         // Setting day for wrap-around from April 2025 to January 2020
         else if ( hour == 23 && min == 59 && sec == 59 && day == 30 && month == 4 && year == 2025) begin 
           day_of_week <= calc_day_of_week(1, 1, 2020);
           end 
         // Setting day for leap year
         else if ( hour == 23 && min == 59 && sec == 59 && day == 28 && month == 2 && days_in_month(month, year) == 29) begin 
           day_of_week <= calc_day_of_week(29, 2, year);
           end 
          // Setting day for non leap year
          else if ( hour == 23 && min == 59 && sec == 59 && day == 28 && month == 2 && days_in_month(month, year) == 28) begin 
           day_of_week <= calc_day_of_week(1, 3, year);
           end
           // Normal case
           else begin  
           day_of_week <= calc_day_of_week(day, month, year);
         end
         // Ensuring that alarm and timer only ring ONCE
         if (timer_buzzer) begin
           timer_buzzer <= 0; // Turning the buzzer OFF
         end
         if (alarm_buzzer) begin 
           alarm_buzzer <= 0; // Turning the buzzer OFF
         end

         //$display("Sanity Check: Time: %02d %02d %02d, Alarm TIme: %02d %02d %02d", hour, min, sec, alarm_hour, alarm_min, alarm_sec);
         // Triggering Alarm
         if (alarm_enable && alarm_hour == 0 && alarm_min == 0 && alarm_sec == 0 && 
           hour == 23 && min == 59 && sec == 59) begin
           alarm_buzzer <= 1;
           //alarm_triggered <= 1;
         end else if (alarm_enable &&
           hour == alarm_hour && min == alarm_min && sec + 1 == alarm_sec) begin
           alarm_buzzer <= 1;
           //alarm_triggered <= 1;
         end

         // Timer Check
         if (timer_enable) begin
           timer_count_min <= timer_min;
           timer_count_sec <= timer_sec;
           //timer_running <= 1;
           timer_buzzer <= 0;
         end
         // Triggering Timer 
         if (timer_enable) begin
           //$display("LEFT TIME: %02d %02d", timer_count_min, timer_count_sec);
           if (timer_count_min == 0 && timer_count_sec == 2) begin
             timer_buzzer <= 1;
             //timer_running <= 0; // Turning it OFF 
             timer_count_sec <= 0; // Manually resetting timer to 00 00 again
           end else begin // Decrementing (minutes/seconds) otherwise
             if (timer_count_sec == 0) begin
               if (timer_count_min > 0) begin
                 timer_count_min <= timer_count_min - 1;
                 timer_count_sec <= 59;
               end
             end else begin
               timer_count_sec <= timer_count_sec - 1;
             end
           end
         end
       end
     end
     endmodule

FinalProject/tb_clock.v
// Setting timescale
`timescale 1s/1ms

module tb_clock;

// Initializing input and output variables

reg clk = 0;
reg reset = 0;

reg [4:0] set_hour = 0;
reg [5:0] set_min = 0, set_sec = 0;
reg [4:0] set_day = 1;
reg [3:0] set_month = 1;
reg [11:0] set_year = 2020;

reg [4:0] alarm_hour = 0;
reg [5:0] alarm_min = 0, alarm_sec = 0;
reg alarm_enable = 0;

reg [5:0] timer_min = 0, timer_sec = 0;
reg timer_enable = 0;

wire AM_enabled;
wire [4:0] hour;
wire [5:0] min, sec;
wire [4:0] day;
wire [3:0] month;
wire [11:0] year;
wire [2:0] day_of_week;
wire [5:0] timer_count_min, timer_count_sec;
wire alarm_buzzer, timer_buzzer;

// Initializing some variables
integer file, mode, res;
integer display_mode = 2;
integer ticks_after_event = 0;
//assign timer_count_min = 6'd0;
//assign timer_count_sec = 6'd0;

// Instantiating Module of Clock
digital_clock uut (
  .clk(clk), .reset(reset), .AM_enabled(AM_enabled),
  .set_hour(set_hour), .set_min(set_min), .set_sec(set_sec),
  .set_day(set_day), .set_month(set_month), .set_year(set_year),
  .alarm_hour(alarm_hour), .alarm_min(alarm_min), .alarm_sec(alarm_sec),
  .alarm_enable(alarm_enable),
  .timer_min(timer_min), .timer_sec(timer_sec),
  .timer_enable(timer_enable),
  .hour(hour), .min(min), .sec(sec),
  .day(day), .month(month), .year(year), .day_of_week(day_of_week),
  .timer_count_min(timer_count_min), .timer_count_sec(timer_count_sec),
  .alarm_buzzer(alarm_buzzer), .timer_buzzer(timer_buzzer)
);


reg [8*10:1] day_names [0:6];
always #0.5 clk = ~clk;  
integer h_waste, m_waste, s_waste;

// Setting Clock cycle as 0.5 seconds as changes are only read at positive edge of clock 
// (if clock period was kept as 1 second, changes would be read every two seconds instead of 1)

// Reading data from text file for which Mode to follow
initial begin 
  file = $fopen("input.txt", "r");
  if (!file) begin
    $display("Cannot open input.txt");
    $finish;
  end
  $dumpfile("clock.vcd");
  $dumpvars(1, tb_clock, uut);  // Dump all signals in testbench and UUT
  while (!$feof(file)) begin
    res = $fscanf(file, "%d", mode); 
    day_names[0] = "Sunday";
    day_names[1] = "Monday";
    day_names[2] = "Tuesday";
    day_names[3] = "Wednesday";
    day_names[4] = "Thursday";
    day_names[5] = "Friday";
    day_names[6] = "Saturday";

    // If Mode is either 1 or 2, displaying time (5 times) in 12 hour or
    // 24 hour format respectively
    if (mode == 1 || mode == 2) begin
      repeat (5) begin
        #1;
        // Checking if timer or alarm rings while the repeat block is
        // active
        if (alarm_buzzer) begin
          $display("ALARM RINGING! Time: %02d:%02d:%02d", hour, min, sec);
          alarm_enable = 0; // Turning the alarm OFF
          ticks_after_event = 0;
        end 
        if (timer_buzzer) begin // It is an 'if' statement, not an 'else if' as both a timer and an alarm may be active
          $display("TIMER DONE!");
          timer_enable = 0; // Turning the timer OFF
          ticks_after_event = 0;
        end if (mode == 1) begin // 12 hour time format
          $display("Time: %02d:%02d:%02d %s | Date: %02d-%02d-%04d (%s)",
            (hour == 0) ? 12 : (hour > 12 ? hour - 12 : hour),
            min, sec,
            (AM_enabled) ? "AM" : "PM", // AM or PM
            day, month, year, day_names[day_of_week]);
        end else begin // 24 hour time format
          $display("Time: %02d:%02d:%02d | Date: %02d-%02d-%04d (%s)",
            hour, min, sec, day, month, year, day_names[day_of_week]);
        end
      end
    end else if (mode == 3) begin // Setting time and Date Manually
      res = $fscanf(file, "%d %d %d %d %d %d",
        set_hour, set_min, set_sec,
        set_day, set_month, set_year); 
      $display("Setting time to %02d:%02d:%02d and date to %02d-%02d-%04d",
        set_hour, set_min, set_sec, set_day, set_month, set_year);
      reset = 1; #0.5; reset = 0;
    end else if (mode == 4 && !alarm_enable) begin // Setting alarm
      // second condition is to ensure only one alarm is set at once
      res = $fscanf(file, "%d %d %d", alarm_hour, alarm_min, alarm_sec);
      alarm_enable = 1; // Turning the alarm ON
      $display("Alarm set for %02d:%02d:%02d", alarm_hour, alarm_min, alarm_sec);
    end else if(mode == 4 && alarm_enable) begin 
      $display("One Alarm has already been set for %d:%d:%d", alarm_hour, alarm_min, alarm_sec);
      res = $fscanf(file, "%d %d %d", h_waste, m_waste, s_waste); // dummy variables so next line can be read
    end else if (mode == 5 && !timer_enable) begin // Setting timer 
      // second condition is to ensure only one timer is set at once
      res = $fscanf(file, "%d %d", timer_min, timer_sec); 
      timer_enable = 1; // Turning the timer ON  
      $display("Current time: %02d : %02d : %02d, Timer set for %02d minutes %02d seconds", hour, min, sec, timer_min, timer_sec);
    end else if(mode == 5 && timer_enable) begin
      $display("One timer has already been set for %02d minutes %02d seconds", timer_min, timer_sec);
      res = $fscanf(file, "%d %d", m_waste, s_waste); // dummy variables so next line can be read
    end else if (mode == 6) begin 
      set_hour = 0;
      set_min = 0;
      set_sec = 0;
      set_day = 1;
      set_month = 1;
      set_year = 2020;
      timer_enable = 0;
      alarm_enable = 0;
      reset = 1; #0.5; reset = 0;
      $display("RESET! Time: %02d:%02d:%02d | Date: %02d-%02d-%04d (%s)", hour, min, sec, day, month, year, day_names[day_of_week]);
    end else begin
      $display("Unknown mode: %d", mode);
    end
    //#1;
  end
  $fclose(file);

  repeat (300) begin
    #1; 
    if (alarm_buzzer) begin // Ringing alarm (when it occurs outside Mode 1 or 2)
      $display("ALARM RINGING! Time: %02d:%02d:%02d | Date: %02d-%02d-%04d", hour, min, sec, day, month, year);
      alarm_enable = 0; // Turning the alarm OFF
      ticks_after_event = 0;
    end if (timer_buzzer) begin  // Ringing timer (when it occurs outside Mode 1 or 2)
      $display("TIMER DONE! Time: %02d:%02d:%02d | Date: %02d-%02d-%04d", hour, min, sec, day, month, year);
      timer_enable = 0; // Turning the timer OFF
      ticks_after_event = 0;
    end /*else if (timer_count_min || timer_count_sec) begin
    $display("TIMER: %02d:%02d", timer_count_min, timer_count_sec);
    ticks_after_event = 0;
  end*/ 
 // Displaying time normally only when neither timer nor alarm buzzers are
 // active
 if(alarm_buzzer == 0 && timer_buzzer == 0) begin // Displaying time in either 24 hour or 12 hour format
   if (display_mode == 1)
     $display("Time: %02d:%02d:%02d %s | Date: %02d-%02d-%04d",
   (hour == 0) ? 12 : (hour > 12 ? hour - 12 : hour),
   min, sec,
   (AM_enabled) ? "AM" : "PM",
   day, month, year);
 else
   $display("Time: %02d:%02d:%02d | Date: %02d-%02d-%04d (%s)",
 hour, min, sec, day, month, year, day_names[day_of_week]);
    ticks_after_event = ticks_after_event + 1;
  end
  //$display("Sanity Check: alarm buzzer: %d, timer buzzer: %d, timer: %d: %d, alarm enabled? %d, ticks after event: %d", alarm_buzzer, timer_buzzer, timer_count_min, timer_count_sec, alarm_enable, ticks_after_event);
  // The below line is to ensure that as long as timer/alarm is active program
  // continues to show time even though Mode 1 or Mode 2 is not specified
  // suffeciently for timer/alarm to run down and ring.
  if (!alarm_buzzer && !timer_buzzer && !timer_enable &&
    ticks_after_event > 5 && !alarm_enable) begin
    $display("Simulation complete.");
    $finish;
  end
end

$display("Simulation timeout.");
$finish;
      end
      endmodule

FinalProject/clock.vcd
$date
	Wed May  7 21:55:51 2025
$end
$version
	Icarus Verilog
$end
$timescale
	1ms
$end
$scope module tb_clock $end
$var wire 12 ! year [11:0] $end
$var wire 6 " timer_count_sec [5:0] $end
$var wire 6 # timer_count_min [5:0] $end
$var wire 1 $ timer_buzzer $end
$var wire 6 % sec [5:0] $end
$var wire 4 & month [3:0] $end
$var wire 6 ' min [5:0] $end
$var wire 5 ( hour [4:0] $end
$var wire 3 ) day_of_week [2:0] $end
$var wire 5 * day [4:0] $end
$var wire 1 + alarm_buzzer $end
$var wire 1 , AM_enabled $end
$var reg 1 - alarm_enable $end
$var reg 5 . alarm_hour [4:0] $end
$var reg 6 / alarm_min [5:0] $end
$var reg 6 0 alarm_sec [5:0] $end
$var reg 1 1 clk $end
$var reg 1 2 reset $end
$var reg 5 3 set_day [4:0] $end
$var reg 5 4 set_hour [4:0] $end
$var reg 6 5 set_min [5:0] $end
$var reg 4 6 set_month [3:0] $end
$var reg 6 7 set_sec [5:0] $end
$var reg 12 8 set_year [11:0] $end
$var reg 1 9 timer_enable $end
$var reg 6 : timer_min [5:0] $end
$var reg 6 ; timer_sec [5:0] $end
$var integer 32 < display_mode [31:0] $end
$var integer 32 = file [31:0] $end
$var integer 32 > h_waste [31:0] $end
$var integer 32 ? m_waste [31:0] $end
$var integer 32 @ mode [31:0] $end
$var integer 32 A res [31:0] $end
$var integer 32 B s_waste [31:0] $end
$var integer 32 C ticks_after_event [31:0] $end
$upscope $end
$scope module tb_clock $end
$scope module uut $end
$var wire 1 - alarm_enable $end
$var wire 5 D alarm_hour [4:0] $end
$var wire 6 E alarm_min [5:0] $end
$var wire 6 F alarm_sec [5:0] $end
$var wire 1 1 clk $end
$var wire 1 2 reset $end
$var wire 5 G set_day [4:0] $end
$var wire 5 H set_hour [4:0] $end
$var wire 6 I set_min [5:0] $end
$var wire 4 J set_month [3:0] $end
$var wire 6 K set_sec [5:0] $end
$var wire 12 L set_year [11:0] $end
$var wire 1 9 timer_enable $end
$var wire 6 M timer_min [5:0] $end
$var wire 6 N timer_sec [5:0] $end
$var reg 1 , AM_enabled $end
$var reg 1 + alarm_buzzer $end
$var reg 5 O day [4:0] $end
$var reg 3 P day_of_week [2:0] $end
$var reg 5 Q hour [4:0] $end
$var reg 6 R min [5:0] $end
$var reg 4 S month [3:0] $end
$var reg 6 T sec [5:0] $end
$var reg 1 $ timer_buzzer $end
$var reg 6 U timer_count_min [5:0] $end
$var reg 6 V timer_count_sec [5:0] $end
$var reg 12 W year [11:0] $end
$upscope $end
$upscope $end
$enddefinitions $end
$comment Show the parameter values. $end
$dumpall
$end
#0
$dumpvars
b11111101000 W
b0 V
b0 U
b111001 T
b101 S
b111011 R
b1000 Q
bx P
b101 O
b0 N
b0 M
b11111101000 L
b111001 K
b101 J
b111011 I
b1000 H
b101 G
b0 F
b0 E
b0 D
b0 C
bx B
b110 A
b11 @
bx ?
bx >
b10000000000000000000000000000011 =
b10 <
b0 ;
b0 :
09
b11111101000 8
b111001 7
b101 6
b111011 5
b1000 4
b101 3
12
01
b0 0
b0 /
b0 .
0-
0,
0+
b101 *
bx )
b1000 (
b111011 '
b101 &
b111001 %
0$
b0 #
b0 "
b11111101000 !
$end
#500
b0 )
b0 P
b111010 %
b111010 T
1,
b1 A
b1 @
02
11
#1000
01
#1500
b111011 %
b111011 T
11
#2000
01
#2500
b1001 (
b1001 Q
b0 '
b0 R
b0 %
b0 T
11
#3000
01
#3500
b1 %
b1 T
11
#4000
01
#4500
b10 %
b10 T
11
#5000
01
#5500
b1010 "
b1010 V
b11 %
b11 T
11
1-
b1010 0
b1010 F
19
b1 A
b1010 ;
b1010 N
b1 @
#6000
01
#6500
b1001 "
b1001 V
b100 %
b100 T
11
#7000
01
#7500
b1000 "
b1000 V
b101 %
b101 T
11
#8000
01
#8500
b111 "
b111 V
b110 %
b110 T
11
#9000
01
#9500
b110 "
b110 V
b111 %
b111 T
11
#10000
01
#10500
b11111100100 !
b11111100100 W
b1 &
b1 S
b1 *
b1 O
b0 %
b0 T
b0 (
b0 Q
11
12
b110 A
b11111100100 8
b11111100100 L
b1 6
b1 J
b1 3
b1 G
b0 7
b0 K
b0 5
b0 I
b0 4
b0 H
b11 @
#11000
01
b1010 B
b0 ?
b1 A
b10 @
02
#11500
b101 "
b101 V
b11 )
b11 P
b1 %
b1 T
11
#12000
01
#12500
b100 "
b100 V
b10 %
b10 T
11
#13000
01
#13500
b11 "
b11 V
b11 %
b11 T
11
#14000
01
#14500
b10 "
b10 V
b100 %
b100 T
11
#15000
01
#15500
1$
b0 "
b0 V
b101 %
b101 T
11
#16000
01
b1 @
09
#16500
0$
b110 %
b110 T
11
#17000
01
#17500
b111 %
b111 T
11
#18000
01
#18500
b1000 %
b1000 T
11
#19000
01
#19500
b1001 %
b1001 T
11
#20000
01
#20500
1+
b1010 %
b1010 T
11
#21000
01
b0 A
0-
#21500
0+
b1011 %
b1011 T
11
#22000
01
#22500
b1100 %
b1100 T
11
#23000
01
#23500
b1101 %
b1101 T
11
#24000
01
#24500
b1110 %
b1110 T
11
#25000
01
#25500
b1111 %
b1111 T
11
#26000
01
#26500
b10000 %
b10000 T
11
#27000
01
b1 C
#27500
b10001 %
b10001 T
11
#28000
01
b10 C
#28500
b10010 %
b10010 T
11
#29000
01
b11 C
#29500
b10011 %
b10011 T
11
#30000
01
b100 C
#30500
b10100 %
b10100 T
11
#31000
01
b101 C
#31500
b10101 %
b10101 T
11
#32000
01
b110 C
